frilouz.py
mabgast.py
frilouz-0.0.2.dist-info/LICENSE
frilouz-0.0.2.dist-info/METADATA
frilouz-0.0.2.dist-info/WHEEL
frilouz-0.0.2.dist-info/top_level.txt
frilouz-0.0.2.dist-info/RECORD
